slack_alerter/__init__.py
slack_alerter/alerter.py
slack_alerter-0.1.4.dist-info/LICENSE
slack_alerter-0.1.4.dist-info/METADATA
slack_alerter-0.1.4.dist-info/WHEEL
slack_alerter-0.1.4.dist-info/top_level.txt
slack_alerter-0.1.4.dist-info/RECORD
