Metadata-Version: 2.1
Name: slack-alerter
Version: 0.1.4
Summary: Slack Crash Alerter Client using Incoming Webhooks
Home-page: https://github.com/hritikkarwasra/slack-alerter
Author: Hritik Karwasra
Author-email: khrithik0806@gmail.com
License: MIT
Project-URL: Documentation, https://github.com/hritikkarwasra/slack-alerter
Project-URL: Source, https://github.com/hritikkarwasra/slack-alerter
Keywords: python,Slack,Alerter,Crash Alerter
Platform: UNKNOWN
Classifier: License :: OSI Approved :: MIT License
Classifier: Development Status :: 3 - Alpha
Classifier: Intended Audience :: Developers
Classifier: Programming Language :: Python :: 3.8
Classifier: Programming Language :: Python :: 3.9
Classifier: Programming Language :: Python :: 3.10
Classifier: Programming Language :: Python :: 3.11
Classifier: Operating System :: MacOS :: MacOS X
Requires-Python: >=3.8
License-File: LICENSE
Requires-Dist: requests==2.*
